flux0_ai/__init__.py
flux0_ai-0.1.0b4.dist-info/METADATA
flux0_ai-0.1.0b4.dist-info/WHEEL
flux0_ai-0.1.0b4.dist-info/entry_points.txt
flux0_ai-0.1.0b4.dist-info/licenses/LICENSE
flux0_ai-0.1.0b4.dist-info/RECORD
