Metadata-Version: 2.4
Name: flux0-ai
Version: 0.1.0b4
License-File: LICENSE
Requires-Python: >=3.13
Requires-Dist: flux0-cli==0.1.0-beta.1
Requires-Dist: flux0-server==0.1.0-beta.4
Provides-Extra: examples
Requires-Dist: langchain[openai]>=0.3.26; extra == 'examples'
Requires-Dist: langgraph>=0.5.1; extra == 'examples'
